LICENSE
README.md
setup.py
Pyhandling.egg-info/PKG-INFO
Pyhandling.egg-info/SOURCES.txt
Pyhandling.egg-info/dependency_links.txt
Pyhandling.egg-info/requires.txt
Pyhandling.egg-info/top_level.txt
pyhandling/__init__.py
pyhandling/annotations.py
pyhandling/binders.py
pyhandling/branchers.py
pyhandling/checkers.py
pyhandling/collections_.py
pyhandling/errors.py
pyhandling/language.py
pyhandling/shortcuts.py
pyhandling/synonyms.py
pyhandling/tools.py
pyhandling/utils.py
tests/__init__.py
tests/mocks.py
tests/test_binders.py
tests/test_branchers.py
tests/test_checkers.py
tests/test_collections_.py
tests/test_language.py
tests/test_shortcuts.py
tests/test_synonyms.py
tests/test_tools.py
tests/test_utils.py