Metadata-Version: 2.1
Name: Pyhandling
Version: 2.2.0
Summary: Library for metaprogramming
Home-page: https://github.com/TheArtur128/Pyhandling
Download-URL: https://github.com/TheArtur128/Pyhandling/archive/refs/tags/v2.2.0.zip
Author: Arthur
Author-email: s9339307190@gmail.com
License: GNU General Public License v3.0
Keywords: syntax,library,utils,logging,metaprogramming,annotations,immutability,data-structures,error-handling,handling,checking,utils-library,pseudo-operators
Classifier: Programming Language :: Python :: 3.11
Requires-Python: >=3.11
License-File: LICENSE
